double_stub/__init__.py
double_stub/__main__.py
double_stub/batch.py
double_stub/cli.py
double_stub/constants.py
double_stub/core.py
double_stub/export.py
double_stub/frequency_sweep.py
double_stub/py.typed
double_stub/utils.py
double_stub/validation.py
double_stub/visualization.py
double_stub-2.5.0.dist-info/licenses/LICENSE
double_stub-2.5.0.dist-info/METADATA
double_stub-2.5.0.dist-info/WHEEL
double_stub-2.5.0.dist-info/entry_points.txt
double_stub-2.5.0.dist-info/top_level.txt
double_stub-2.5.0.dist-info/RECORD
