Metadata-Version: 2.4
Name: double-stub
Version: 2.5.0
Summary: Double-stub impedance matching calculator for RF/microwave engineering
Author: Efren Rodriguez Rodriguez
License: MIT
Project-URL: Homepage, https://github.com/EfrenPy/Double-Stub-Impedance-Matching
Project-URL: Repository, https://github.com/EfrenPy/Double-Stub-Impedance-Matching
Project-URL: Issues, https://github.com/EfrenPy/Double-Stub-Impedance-Matching/issues
Keywords: impedance-matching,rf-engineering,transmission-line,smith-chart
Classifier: Development Status :: 4 - Beta
Classifier: Intended Audience :: Science/Research
Classifier: License :: OSI Approved :: MIT License
Classifier: Programming Language :: Python :: 3
Classifier: Programming Language :: Python :: 3.10
Classifier: Programming Language :: Python :: 3.12
Classifier: Programming Language :: Python :: 3.13
Classifier: Topic :: Scientific/Engineering :: Physics
Requires-Python: >=3.10
License-File: LICENSE
Requires-Dist: numpy>=1.19.0
Requires-Dist: scipy>=1.5.0
Provides-Extra: plot
Requires-Dist: matplotlib>=3.3.0; extra == "plot"
Provides-Extra: dev
Requires-Dist: pytest>=7.0; extra == "dev"
Requires-Dist: pytest-cov>=4.0; extra == "dev"
Requires-Dist: flake8>=6.0; extra == "dev"
Requires-Dist: mypy>=1.0; extra == "dev"
Dynamic: license-file
